Dsutilities/__init__.py
Dsutilities/utilitites.py
dsutilities-0.0.1.dist-info/METADATA
dsutilities-0.0.1.dist-info/WHEEL
dsutilities-0.0.1.dist-info/top_level.txt
dsutilities-0.0.1.dist-info/RECORD
