Metadata-Version: 2.1
Name: dsutilities
Version: 0.0.1
Summary: DS Utilities
Home-page: UNKNOWN
Author: Mithridates
Author-email: <mmithridatess@gmail.com>
License: UNKNOWN
Keywords: python,video,stream,video stream,camera stream,sockets
Platform: UNKNOWN
Classifier: Development Status :: 1 - Planning
Classifier: Intended Audience :: Developers
Classifier: Programming Language :: Python :: 3
Classifier: Operating System :: Unix
Classifier: Operating System :: MacOS :: MacOS X
Classifier: Operating System :: Microsoft :: Windows
Requires-Dist: tensorflow
Requires-Dist: numpy
